README.md
setup.cfg
setup.py
TwoFactor/__init__.py
TwoFactor.egg-info/PKG-INFO
TwoFactor.egg-info/SOURCES.txt
TwoFactor.egg-info/dependency_links.txt
TwoFactor.egg-info/top_level.txt