Metadata-Version: 1.0
Name: TwoFactor
Version: 1.0
Summary: TwoFactor
Home-page: https://github.com/Zenitsudeck/TwoFactor
Author: Zenitsudeck
Author-email: UNKNOWN
License: UNKNOWN
Platform: UNKNOWN
